nfldata/__init__.py
nfldata/__main__.py
nfldata/encoder.py
nfldata/typing_utils.py
nfldata/util.py
nfldata/controllers/__init__.py
nfldata/controllers/security_controller_.py
nfldata/models/__init__.py
nfldata/models/base.py
nfldata/models/base_model_.py
nfldata/models/field_goal.py
nfldata/models/field_goal_all_of.py
nfldata/models/game.py
nfldata/models/game_all_of.py
nfldata/models/kicker.py
nfldata/models/kicker_all_of.py
nfldata/models/team.py
nfldata/models/team_all_of.py
nfldata/models/team_short_code_enum.py
nfldata/models/weather.py
nfldata/models/weather_all_of.py
nfldata/openapi/openapi.yaml
nfldata/test/__init__.py
nfldata-0.1.0.dist-info/METADATA
nfldata-0.1.0.dist-info/WHEEL
nfldata-0.1.0.dist-info/licenses/LICENSE
nfldata-0.1.0.dist-info/RECORD
