Metadata-Version: 2.1
Name: nfldata
Version: 0.1.0
Summary: NFL Kicking Data
Project-URL: Homepage, https://github.com/mczajkow/nfldata
Project-URL: Bug Tracker, https://github.com/mczajkow/nfldata/issues
Author-email: Michael Czajkowski <michael@czajkowski.ws>
License-File: LICENSE
Classifier: License :: OSI Approved :: MIT License
Classifier: Operating System :: OS Independent
Classifier: Programming Language :: Python :: 3
Requires-Python: >=3.7
